NDETCStemmer/BestWordSelector.py
NDETCStemmer/CandidateGenerator.py
NDETCStemmer/ListRules.py
NDETCStemmer/ModelDownloader.py
NDETCStemmer/NDETCStemmer.py
NDETCStemmer/NDETCStemmerAbstract.py
NDETCStemmer/RulesGenerator.py
NDETCStemmer/__init__.py
NDETCStemmer/DictFile/__init__.py
NDETCStemmer/DictFile/compound_word.txt
NDETCStemmer/DictFile/rare_word.txt
NDETCStemmer/DictFile/root_word.txt
NDETCStemmer/DictFile/stopword.txt
NDETCStemmer/Utility/__init__.py
NDETCStemmer/Utility/generator_initiator.py
NDETCStemmer/Utility/normalizer.py
NDETCStemmer/Utility/__pycache__/__init__.cpython-310.pyc
NDETCStemmer/Utility/__pycache__/generator_initiator.cpython-310.pyc
NDETCStemmer/Utility/__pycache__/normalizer.cpython-310.pyc
NDETCStemmer/__pycache__/BestWordSelector.cpython-310.pyc
NDETCStemmer/__pycache__/CandidateGenerator.cpython-310.pyc
NDETCStemmer/__pycache__/ListRules.cpython-310.pyc
NDETCStemmer/__pycache__/ModelDownloader.cpython-310.pyc
NDETCStemmer/__pycache__/NDETCStemmer.cpython-310.pyc
NDETCStemmer/__pycache__/NDETCStemmerAbstract.cpython-310.pyc
NDETCStemmer/__pycache__/RulesGenerator.cpython-310.pyc
NDETCStemmer/__pycache__/__init__.cpython-310.pyc
NDETCStemmer/morphology/__init__.py
NDETCStemmer/morphology/infixrule.py
NDETCStemmer/morphology/particlerule.py
NDETCStemmer/morphology/possessivepronounrule.py
NDETCStemmer/morphology/prefix10rule.py
NDETCStemmer/morphology/prefix1rule.py
NDETCStemmer/morphology/prefix20rule.py
NDETCStemmer/morphology/prefix39rule.py
NDETCStemmer/morphology/prefix6rule.py
NDETCStemmer/morphology/reduplicationrule.py
NDETCStemmer/morphology/simulfixrule.py
NDETCStemmer/morphology/suffix2rule_v2.py
NDETCStemmer/morphology/validsuffixprefix.py
NDETCStemmer/morphology/__pycache__/__init__.cpython-310.pyc
NDETCStemmer/morphology/__pycache__/infixrule.cpython-310.pyc
NDETCStemmer/morphology/__pycache__/particlerule.cpython-310.pyc
NDETCStemmer/morphology/__pycache__/possessivepronounrule.cpython-310.pyc
NDETCStemmer_kaenova-1.4.3.dist-info/LICENSE
NDETCStemmer_kaenova-1.4.3.dist-info/METADATA
NDETCStemmer_kaenova-1.4.3.dist-info/WHEEL
NDETCStemmer_kaenova-1.4.3.dist-info/top_level.txt
NDETCStemmer_kaenova-1.4.3.dist-info/RECORD
