Metadata-Version: 2.1
Name: NDETCStemmer-kaenova
Version: 1.4.3
Summary: Library untuk stemming kata dalam Bahasa Indonesia menggunakan metode Nondeterministic Context
Home-page: https://github.com/kaenova/NDETCStemmer
Keywords: linguistic stemming indonesian bahasa
Classifier: Programming Language :: Python :: 3
Classifier: Intended Audience :: Information Technology
Classifier: Intended Audience :: Science/Research
Classifier: Topic :: Text Processing :: Linguistic
License-File: LICENSE
Requires-Dist: nltk
Requires-Dist: gensim
Requires-Dist: gdown
Requires-Dist: checksumdir
Requires-Dist: huggingface-hub
